dsalg/__init__.py
dsalg-0.0.1.dist-info/LICENSE
dsalg-0.0.1.dist-info/METADATA
dsalg-0.0.1.dist-info/WHEEL
dsalg-0.0.1.dist-info/top_level.txt
dsalg-0.0.1.dist-info/RECORD
